Metadata-Version: 2.1
Name: django-filepond-widget
Version: 0.9.0
Author-email: Jelle Besseling <jelle@pingiun.com>
License: Unlicense
Project-URL: homepage, https://github.com/pingiun/django-filepond-widget
Project-URL: repository, https://github.com/pingiun/django-filepond-widget
Project-URL: documentation, https://github.com/pingiun/django-filepond-widget
Requires-Python: >=3
License-File: LICENSE
